typed_env/__init__.py
typed_env/environ.py
typed_env/initialize.py
typed_env/read_dot_env.py
typed_env-0.2.1.dist-info/DESCRIPTION.rst
typed_env-0.2.1.dist-info/METADATA
typed_env-0.2.1.dist-info/RECORD
typed_env-0.2.1.dist-info/WHEEL
typed_env-0.2.1.dist-info/metadata.json
typed_env-0.2.1.dist-info/top_level.txt
