Metadata-Version: 2.0
Name: typed-env
Version: 0.2.1
Summary: Fast-fail environment variable library.
Home-page: https://github.com/mkurnikov/typed-env
Author: Maxim Kurnikov
Author-email: maxim.kurnikov@gmail.com
License: MIT
Platform: UNKNOWN
Requires-Dist: validators
